[
  {"subject": "Rowling", "relation": "working as for", "object": "Amnesty International"},
  {"subject": "Amnesty International", "relation": "in conceived for", "object": "Harry Potter"},
  {"subject": "Harry Potter", "relation": "attends", "object": "Hogwarts"},
  {"subject": "OBE", "relation": "made", "object": "Companion"},
  {"subject": "Forbes", "relation": "estimated", "object": "Rowling"},
  {"subject": "=", "relation": "=", "object": "Joanne Rowling"},
  {"subject": "Joanne Rowling", "relation": "born on", "object": "July"},
  {"subject": "Rowlings", "relation": "settled in", "object": "Yate"},
  {"subject": "Rowling", "relation": "moved to", "object": "Winterbourne"},
  {"subject": "Rowling", "relation": "began attending", "object": "Church"},
  {"subject": "Rowling", "relation": "joined", "object": "Brownies"},
  {"subject": "Smith", "relation": "writes", "object": "Rowling"},
  {"subject": "Mitford", "relation": "became", "object": "Rowling"},
  {"subject": "Ford Anglia", "relation": "provided from for", "object": "Harris"},
  {"subject": "Rowling", "relation": "moved to in", "object": "Clapham Junction"},
  {"subject": "Amnesty International", "relation": "hired document in", "object": "French"},
  {"subject": "Guardian", "relation": "led move to", "object": "Porto"},
  {"subject": "November", "relation": "teach in", "object": "English"},
  {"subject": "Rowling", "relation": "met", "object": "Jorge Arantes"},
  {"subject": "Jorge Arantes", "relation": "in found shared in", "object": "Jane Austen"},
  {"subject": "London", "relation": "introduce", "object": "Arantes"},
  {"subject": "Rowling", "relation": "finished of", "object": "Harry Potter"},
  {"subject": "Arantes", "relation": "separated on", "object": "November"},
  {"subject": "Jessica", "relation": "went into for left", "object": "Portugal"},
  {"subject": "Rowling", "relation": "moved with to", "object": "Edinburgh"},
  {"subject": "Sean Smith", "relation": "raises of", "object": "Rowling"},
  {"subject": "Pete", "relation": "married within of", "object": "Anne"},
  {"subject": "March", "relation": "seeking", "object": "Rowling"},
  {"subject": "Arantes", "relation": "returned to", "object": "Portugal"},
  {"subject": "Rowling", "relation": "began in", "object": "August"},
  {"subject": "July", "relation": "began teaching at", "object": "Leith Academy"},
  {"subject": "Rowling", "relation": "completed", "object": "Harry Potter"},
  {"subject": "Christopher Little Literary Agency", "relation": "agreed represent", "object": "Rowling"},
  {"subject": "Rowling", "relation": "awarded by", "object": "Scottish Arts Council"},
  {"subject": "Scottish Arts Council", "relation": "support before", "object": "Philosopher"},
  {"subject": "Bloomsbury", "relation": "published", "object": "Philosopher"},
  {"subject": "Stone", "relation": "introduces", "object": "Harry Potter"},
  {"subject": "Ron Weasley", "relation": "defeat", "object": "Lord Voldemort"},
  {"subject": "Rowling", "relation": "received", "object": "US"},
  {"subject": "US", "relation": "auctioned at", "object": "Bologna Children"},
  {"subject": "Rowling", "relation": "suggested", "object": "Harry Potter"},
  {"subject": "Stone", "relation": "released in", "object": "United States"},
  {"subject": "Stone", "relation": "became", "object": "New York Times"},
  {"subject": "Prince", "relation": "released in", "object": "July"},
  {"subject": "Warner Bros.", "relation": "purchased to", "object": "Harry Potter"},
  {"subject": "Warner Bros.", "relation": "announced expanded with", "object": "Rowling"},
  {"subject": "Grindelwald", "relation": "released in", "object": "November"},
  {"subject": "Dumbledore", "relation": "released in", "object": "April"},
  {"subject": "Variety", "relation": "reported", "object": "Warner Bros. Discovery"},
  {"subject": "Warner Bros. Discovery", "relation": "planning continue develop related to", "object": "Wizarding World"},
  {"subject": "UK Press Complaints Commission", "relation": "ruled breached", "object": "Jessica"},
  {"subject": "Forbes", "relation": "named", "object": "Rowling"},
  {"subject": "Forbes", "relation": "concluded due to", "object": "UK"},
  {"subject": "Sunday Times Rich List", "relation": "estimated", "object": "Rowling"},
  {"subject": "Rowling", "relation": "left", "object": "Christopher Little Literary Agency"},
  {"subject": "Christopher Little Literary Agency", "relation": "followed", "object": "Neil Blair"},
  {"subject": "Richard Brooks", "relation": "contacted", "object": "Rowling"},
  {"subject": "Cormoran Strike", "relation": "starring", "object": "Tom Burke"},
  {"subject": "Harry Potter", "relation": "works", "object": "Pottermore"},
  {"subject": "Pottermore", "relation": "rooted in", "object": "Harry Potter"},
  {"subject": "Cursed Child", "relation": "premiered in", "object": "West"},
  {"subject": "Rowling", "relation": "confirmed write", "object": "Harry Potter"},
  {"subject": "Rowling", "relation": "collaborated with", "object": "Jack Thorne"},
  {"subject": "Cursed Child", "relation": "published as in", "object": "July"},
  {"subject": "Harry Potter", "relation": "span of dedicated to of", "object": "Harry Potter"},
  {"subject": "Rowling", "relation": "aimed at", "object": "Harry Potter"},
  {"subject": "Rowling", "relation": "released", "object": "Ickabog"},
  {"subject": "Scholastic", "relation": "held select for", "object": "edition"},
  {"subject": "Christmas Pig", "relation": "guides through", "object": "Land"},
  {"subject": "October", "relation": "became in", "object": "UK"},
  {"subject": "Rowling", "relation": "named", "object": "Jessica Mitford"},
  {"subject": "Mitford", "relation": "run at of fight with", "object": "Reds"},
  {"subject": "Rowling", "relation": "read", "object": "C. S. Lewis"},
  {"subject": "Harry Potter", "relation": "influenced by of as", "object": "Lewis"},
  {"subject": "Harry", "relation": "receives from", "object": "Remus Lupin"},
  {"subject": "Harry", "relation": "draw", "object": "Sword"},
  {"subject": "Dursleys", "relation": "compared to", "object": "Cinderella"},
  {"subject": "Joy Farmer", "relation": "sees between", "object": "Harry"},
  {"subject": "Rowling", "relation": "overarching in", "object": "Harry Potter"},
  {"subject": "Harry", "relation": "looks into", "object": "Mirror"},
  {"subject": "Harry", "relation": "assumes in", "object": "Quirrell"},
  {"subject": "Quirrell", "relation": "opposes", "object": "Snape"},
  {"subject": "Harry Potter", "relation": "occupied of", "object": "New York Times"},
  {"subject": "Harold Bloom", "relation": "regarded", "object": "Rowling"},
  {"subject": "Harry", "relation": "escapes", "object": "Dursleys"},
  {"subject": "Dursleys", "relation": "visit", "object": "Hogwarts"},
  {"subject": "Mary Pharr", "relation": "argues", "object": "Harry Potter"},
  {"subject": "Rowling", "relation": "include", "object": "Marina Warner"},
  {"subject": "English", "relation": "traces from", "object": "Edmund Spenser"},
  {"subject": "Michiko Kakutani", "relation": "praises", "object": "Rowling"},
  {"subject": "Amanda Cockrell", "relation": "suggests", "object": "Harry Potter"},
  {"subject": "Harry Potter", "relation": "have of believe", "object": "Harry Potter"},
  {"subject": "Em McAvan", "relation": "writes to", "object": "Harry Potter"},
  {"subject": "Nancy Stouffer", "relation": "sued", "object": "Rowling"},
  {"subject": "Richard Posner", "relation": "describes", "object": "Stouffer"},
  {"subject": "Rowling", "relation": "brought against of", "object": "Harry Potter"},
  {"subject": "Rowling", "relation": "sold to", "object": "Warner Bros."},
  {"subject": "Rowling", "relation": "started cease of based on from called", "object": "Harry Potter Lexicon"},
  {"subject": "Rowling", "relation": "established", "object": "Volant Charitable Trust"},
  {"subject": "Sarah Brown", "relation": "on of benefit", "object": "Parent Families"},
  {"subject": "Rowling", "relation": "founded known as", "object": "Lumos"},
  {"subject": "Rowling", "relation": "offered match in to", "object": "Lumos"},
  {"subject": "Rowling", "relation": "stated founded fund", "object": "Beira"},
  {"subject": "Beasts", "relation": "Find", "object": "Quidditch"},
  {"subject": "Rowling", "relation": "sold of", "object": "Tales"},
  {"subject": "Rowling", "relation": "composed in sold benefit", "object": "Dyslexia Action"},
  {"subject": "Twitter", "relation": "reach", "object": "Harry Potter"},
  {"subject": "Rowling", "relation": "donated to", "object": "Labour Party"},
  {"subject": "Keir Starmer", "relation": "vote for", "object": "Labour"},
  {"subject": "Rowling", "relation": "criticised", "object": "David Cameron"},
  {"subject": "UK", "relation": "stay in", "object": "European Union"},
  {"subject": "Rowling", "relation": "joined in signing published in", "object": "Guardian"},
  {"subject": "Leveson Inquiry", "relation": "into named", "object": "Rowling"},
  {"subject": "Cameron", "relation": "implement supported", "object": "Hacked Off"},
  {"subject": "Variety", "relation": "wrote", "object": "Rowling"},
  {"subject": "Rowling", "relation": "returned", "object": "Ripple"},
  {"subject": "Hope Award", "relation": "given to by", "object": "Robert F. Kennedy Human Rights"},
  {"subject": "Awards", "relation": "honours", "object": "Rowling"},
  {"subject": "Rowling", "relation": "appointed", "object": "Officer"},
  {"subject": "Rowling", "relation": "shared", "object": "British Academy Film Award"}
]
